welcome_derto/__init__.py
welcome_derto/welcome_derto.py
welcome_derto-0.0.3.dist-info/METADATA
welcome_derto-0.0.3.dist-info/WHEEL
welcome_derto-0.0.3.dist-info/licenses/LICENSE
welcome_derto-0.0.3.dist-info/RECORD
