Metadata-Version: 2.4
Name: welcome_derto
Version: 0.0.3
Summary: Test package, used to print a welcome message depending on user in my organization.
Author-email: Cosimo Di Martino <dertranslations@gmail.com>
License-Expression: MIT
License-File: LICENSE
Classifier: Operating System :: OS Independent
Classifier: Programming Language :: Python :: 3
Requires-Python: >=3.8
